sphinx_library/__init__.py
sphinx_library/about.html
sphinx_library/extralinks.html
sphinx_library/globaltoc.html
sphinx_library/layout.html
sphinx_library/localtoc.html
sphinx_library/readingmodes.html
sphinx_library/sponsors.html
sphinx_library/theme.conf
sphinx_library/theme.py
sphinx_library/static/custom.css
sphinx_library/static/pygments.css
sphinx_library/static/library/library.css
sphinx_library/static/library/type-academy-native.css
sphinx_library/static/library/type-academy.css
sphinx_library/static/library/type-book-native.css
sphinx_library/static/library/type-book.css
sphinx_library/static/library/type-engineer-native.css
sphinx_library/static/library/type-engineer.css
sphinx_library/static/library/type-humanist-native.css
sphinx_library/static/library/type-humanist.css
sphinx_library/static/library/type-swiss-native.css
sphinx_library/static/library/type-swiss.css
sphinx_library-1.1.3.dist-info/licenses/LICENSE.txt
sphinx_library-1.1.3.dist-info/METADATA
sphinx_library-1.1.3.dist-info/WHEEL
sphinx_library-1.1.3.dist-info/entry_points.txt
sphinx_library-1.1.3.dist-info/top_level.txt
sphinx_library-1.1.3.dist-info/RECORD
