Metadata-Version: 2.4
Name: sphinx-library
Version: 1.1.3
Summary: Typography-centric Sphinx theme that reads like a good book.
Author-email: Vince Salvino <salvino@coderedcorp.com>
License-Expression: MIT
Project-URL: Documentation, https://vsalvino.github.io/sphinx-library/
Project-URL: Source, https://github.com/vsalvino/sphinx-library
Classifier: Development Status :: 5 - Production/Stable
Classifier: Framework :: Sphinx
Classifier: Framework :: Sphinx :: Theme
Classifier: Intended Audience :: Developers
Classifier: Operating System :: OS Independent
Classifier: Programming Language :: Python
Classifier: Programming Language :: Python :: 3
Classifier: Topic :: Documentation
Classifier: Topic :: Software Development :: Documentation
License-File: LICENSE.txt
Dynamic: license-file
